README.md
setup.py
fuo_dl/__init__.py
fuo_dl/base_downloader.py
fuo_dl/cli.py
fuo_dl/helpers.py
fuo_dl/manager.py
fuo_dl/progress.py
fuo_dl/py_downloader.py
fuo_dl/statusline.py
fuo_dl/task.py
fuo_dl/ui.py
fuo_dl.egg-info/PKG-INFO
fuo_dl.egg-info/SOURCES.txt
fuo_dl.egg-info/dependency_links.txt
fuo_dl.egg-info/entry_points.txt
fuo_dl.egg-info/requires.txt
fuo_dl.egg-info/top_level.txt