Metadata-Version: 2.1
Name: fuo-dl
Version: 0.3
Summary: feeluown download plugin
Home-page: https://github.com/feeluown/feeluown-download
Author: Cosven
Author-email: yinshaowen241@gmail.com
License: UNKNOWN
Keywords: feeluown,plugin,download
Platform: UNKNOWN
Classifier: Development Status :: 3 - Alpha
Classifier: Programming Language :: Python :: 3.6
Classifier: Programming Language :: Python :: 3.7
Classifier: Programming Language :: Python :: 3.8
Classifier: Programming Language :: Python :: 3 :: Only
